sagemaker_headless_execution_driver/__init__.py
sagemaker_headless_execution_driver/headless_execution.py
sagemaker_headless_execution_driver/notebookrunner.py
sagemaker_headless_execution_driver/sm_engine.py
sagemaker_headless_execution_driver/__pycache__/__init__.cpython-310.pyc
sagemaker_headless_execution_driver/__pycache__/__init__.cpython-311.pyc
sagemaker_headless_execution_driver/__pycache__/headless_execution.cpython-310.pyc
sagemaker_headless_execution_driver/__pycache__/headless_execution.cpython-311.pyc
sagemaker_headless_execution_driver/__pycache__/notebookrunner.cpython-310.pyc
sagemaker_headless_execution_driver/__pycache__/notebookrunner.cpython-311.pyc
sagemaker_headless_execution_driver/__pycache__/sm_engine.cpython-310.pyc
sagemaker_headless_execution_driver/__pycache__/sm_engine.cpython-311.pyc
sagemaker_headless_execution_driver/scripts/headless_execution.sh
sagemaker_headless_execution_driver-0.0.13.dist-info/LICENSE
sagemaker_headless_execution_driver-0.0.13.dist-info/METADATA
sagemaker_headless_execution_driver-0.0.13.dist-info/WHEEL
sagemaker_headless_execution_driver-0.0.13.dist-info/entry_points.txt
sagemaker_headless_execution_driver-0.0.13.dist-info/top_level.txt
sagemaker_headless_execution_driver-0.0.13.dist-info/RECORD
