Metadata-Version: 2.1
Name: sagemaker-headless-execution-driver
Version: 0.0.13
Summary: Execution Driver for Notebook Scheduler
Author: Amazon Web Services
License: 
Project-URL: homepage, https://aws.amazon.com/sagemaker
Classifier: Intended Audience :: Developers
Classifier: Intended Audience :: Science/Research
Classifier: License :: OSI Approved :: Apache Software License
Classifier: Programming Language :: Python
Classifier: Programming Language :: Python :: 3.8
Classifier: Programming Language :: Python :: 3.9
Classifier: Programming Language :: Python :: 3.10
Classifier: Programming Language :: Python :: 3.11
Requires-Python: >=3.8
License-File: LICENSE
Requires-Dist: nbconvert
Requires-Dist: papermill
Provides-Extra: dev
Requires-Dist: black ; extra == 'dev'
Requires-Dist: build ; extra == 'dev'
Provides-Extra: test
Requires-Dist: pytest ; extra == 'test'
Requires-Dist: parameterized ; extra == 'test'
Requires-Dist: ipython ; extra == 'test'
Requires-Dist: ipykernel ; extra == 'test'
